audio_video_tools-0.22.data/scripts/audio-video-tools
mediatools/__init__.py
mediatools/album_art.py
mediatools/audio_lib.py
mediatools/audiofile.py
mediatools/black.jpg
mediatools/blindify.py
mediatools/concat.py
mediatools/creator.py
mediatools/crop.py
mediatools/crop_ratio.py
mediatools/cut.py
mediatools/deshake.py
mediatools/encode.py
mediatools/encoder.py
mediatools/exceptions.py
mediatools/file.py
mediatools/filespecs.py
mediatools/filters.py
mediatools/image2video.py
mediatools/imagefile.py
mediatools/linker.py
mediatools/log.py
mediatools/media-tools.properties
mediatools/media_config.py
mediatools/mediafile.py
mediatools/metadata.py
mediatools/mux.py
mediatools/options.py
mediatools/poster.py
mediatools/rescale.py
mediatools/resolution.py
mediatools/reverse.py
mediatools/shake.py
mediatools/slideshow.py
mediatools/speed.py
mediatools/stack.py
mediatools/utilities.py
mediatools/version.py
mediatools/video-720p.mp4
mediatools/videofile.py
mediatools/volume.py
mediatools/white.jpg
audio_video_tools-0.22.dist-info/LICENSE
audio_video_tools-0.22.dist-info/METADATA
audio_video_tools-0.22.dist-info/WHEEL
audio_video_tools-0.22.dist-info/entry_points.txt
audio_video_tools-0.22.dist-info/top_level.txt
audio_video_tools-0.22.dist-info/RECORD
